{
  "pools": [
    {
      "rolls": 1,
      "entries": [
        {
          "type": "minecraft:item",
          "name": "minecraft:stick",
          "conditions": [],
          "functions": [
            {
              "function": "minecraft:set_name",
              "entity": "this",
              "name": "棒",
              "target": "item_name"
            },
            {
              "function": "minecraft:set_lore",
              "entity": "this",
              "lore": [
                {
                  "text": "素材",
                  "color": "dark_gray",
                  "bold": false,
                  "italic": false
                },
                {
                  "text": "一部の木製のアイテムの制作に使用される",
                  "color": "gray",
                  "bold": false,
                  "italic": false
                }
              ],
              "mode": "replace_all"
            },
            {
              "function": "minecraft:set_custom_data",
              "tag": "{id:\"stick\"}"
            }
          ]
        }
      ]
    }
  ]
}